fasttq/__init__.py
fasttq/client.py
fasttq/queue.py
fasttq/worker.py
fasttq-1.0.11.dist-info/LICENSE
fasttq-1.0.11.dist-info/METADATA
fasttq-1.0.11.dist-info/WHEEL
fasttq-1.0.11.dist-info/requirements.txt
fasttq-1.0.11.dist-info/top_level.txt
fasttq-1.0.11.dist-info/RECORD
